crawlipt/__init__.py
crawlipt/__version__.py
crawlipt/action.py
crawlipt/annotation.py
crawlipt/condition.py
crawlipt/error.py
crawlipt/pojo.py
crawlipt/script.py
crawlipt/actions/__init__.py
crawlipt/actions/alert.py
crawlipt/actions/click.py
crawlipt/actions/get.py
crawlipt/actions/input.py
crawlipt/actions/redirect.py
crawlipt/actions/scroll.py
crawlipt/actions/select.py
crawlipt/actions/slide.py
crawlipt/actions/switch.py
crawlipt/actions/util.py
crawlipt/actions/window.py
crawlipt/conditions/__init__.py
crawlipt/conditions/element.py
crawlipt/conditions/frame.py
crawlipt/conditions/presence.py
crawlipt/conditions/text.py
crawlipt/conditions/visibility.py
crawlipt-0.1.4.dist-info/LICENSE
crawlipt-0.1.4.dist-info/METADATA
crawlipt-0.1.4.dist-info/WHEEL
crawlipt-0.1.4.dist-info/top_level.txt
crawlipt-0.1.4.dist-info/RECORD
