Metadata-Version: 2.1
Name: crawlipt
Version: 0.1.4
Summary: The script for selenium in python
Home-page: https://github.com/WwwwwyDev/crawlipt
Author: WwwwwyDev
Author-email: wwy20001014@foxmail.com
License: MIT
Classifier: License :: OSI Approved :: MIT License
Classifier: Programming Language :: Python
Classifier: Programming Language :: Python :: 3
Classifier: Programming Language :: Python :: 3.10
Classifier: Programming Language :: Python :: Implementation :: CPython
Classifier: Programming Language :: Python :: Implementation :: PyPy
Requires-Python: >=3.10.0
License-File: LICENSE
Requires-Dist: selenium >=4.0.0
